chatforward/__init__.py
chatforward/chatforward.py
chatforward/cli.py
chatforward-0.0.1.dist-info/AUTHORS.rst
chatforward-0.0.1.dist-info/LICENSE
chatforward-0.0.1.dist-info/METADATA
chatforward-0.0.1.dist-info/WHEEL
chatforward-0.0.1.dist-info/entry_points.txt
chatforward-0.0.1.dist-info/top_level.txt
chatforward-0.0.1.dist-info/RECORD
